logs/__init__.py
src/__init__.py
src/detection.py
tests/__init__.py
tests/test_data_file.py
tests/test_regex.py
tests/test_regex_file.py
packageSensitiveInfo-1.0.0.dist-info/METADATA
packageSensitiveInfo-1.0.0.dist-info/WHEEL
packageSensitiveInfo-1.0.0.dist-info/top_level.txt
packageSensitiveInfo-1.0.0.dist-info/RECORD
