Metadata-Version: 2.1
Name: packageSensitiveInfo
Version: 1.0.0
Summary: It contains data and regex patterns in 2 separate files. My package validates how many regex patterns matches the data.
Home-page: UNKNOWN
Author: Simran
Author-email: simran.saxena@dataverze.ai
License: UNKNOWN
Platform: UNKNOWN
Classifier: Programming Language :: Python :: 3
Requires-Dist: black ==24.2.0
Requires-Dist: pytest ==8.0.2
Requires-Dist: setuptools ==59.6.0
Requires-Dist: twine ==5.0.0
Requires-Dist: wheel ==0.42.0
